failure_api/__init__.py
failure_api/communication_models/__init__.py
failure_api/communication_models/active_communication.py
failure_api/communication_models/adversarial_jamming_model.py
failure_api/communication_models/base_communication_model.py
failure_api/communication_models/delay_based_model.py
failure_api/communication_models/distance_based_model.py
failure_api/communication_models/markov_model.py
failure_api/communication_models/matrix_model.py
failure_api/communication_models/probabilistic_model.py
failure_api/communication_models/signal_based_model.py
failure_api/noise_models/__init__.py
failure_api/noise_models/base_noise_model.py
failure_api/noise_models/custom_noise.py
failure_api/noise_models/gaussian_noise.py
failure_api/noise_models/laplacian_noise.py
failure_api/wrappers/__init__.py
failure_api/wrappers/base_wrapper.py
failure_api/wrappers/communication_wrapper.py
failure_api/wrappers/noise_wrapper.py
failure_api/wrappers/sharedobs_wrapper.py
utils/__init__.py
utils/position_utils.py
failure_api-0.1.7.dist-info/METADATA
failure_api-0.1.7.dist-info/WHEEL
failure_api-0.1.7.dist-info/top_level.txt
failure_api-0.1.7.dist-info/RECORD
